gym_holdem/__init__.py
gym_holdem/envs/__init__.py
gym_holdem/envs/holdem_env.py
gym_holdem/holdem/__init__.py
gym_holdem/holdem/bet_round.py
gym_holdem/holdem/game.py
gym_holdem/holdem/player.py
gym_holdem/holdem/poker_rule_violation_exception.py
gym_holdem/holdem/pot.py
gym_holdem/holdem/table.py
gym_holdem-0.1.1.dist-info/LICENSE
gym_holdem-0.1.1.dist-info/WHEEL
gym_holdem-0.1.1.dist-info/METADATA
gym_holdem-0.1.1.dist-info/RECORD
