Metadata-Version: 2.1
Name: gym-holdem
Version: 0.1.1
Summary: 
License: MIT
Author: Jan Adä
Requires-Python: >=3.6,<4.0
Classifier: License :: OSI Approved :: MIT License
Classifier: Programming Language :: Python :: 3
Classifier: Programming Language :: Python :: 3.6
Classifier: Programming Language :: Python :: 3.7
Requires-Dist: gym (>=0.12.1,<0.13.0)
Requires-Dist: pokereval-cactus (>=0.1.0,<0.2.0)
Requires-Dist: pytest (>=4.5,<5.0)
Requires-Dist: pytest-azurepipelines (>=0.6.0,<0.7.0)
